[{"userID":1,"firstName":"Emma","lastName":"Walker","email":"emma.walker@example.com","userName":"emwalker","passWord":"$2b$10$3JBXoQSjX8wqiAMzfKk4U.E1BAFoTG1S1hAHkM3dUwtZP3orXFAQS"},{"userID":2,"firstName":"Emma","lastName":"Walker","email":"emma.walker@example.com","userName":"emwalker","passWord":"$2b$10$PEIB45sJd9fxFcxI8.SM..Dwqls89bcXNGbfV.KfIbY86fbTSAonq"},{"userID":3,"firstName":"Liam","lastName":"Hughes","email":"liam.hughes@example.com","userName":"liamh","passWord":"$2b$10$lSfCuS4.il4newqBL1USxutcpb7lqZ9W4/hPen2/Ko37CAKlw792y"},{"userID":4,"firstName":"Noah","lastName":"Fischer","email":"noah.fischer@example.com","userName":"noahf","passWord":"$2b$10$XiNX2LTBMIjW95nxy6NcXOVzPJsf1rckuYjNBZOddTXCOERLqq7.2"},{"userID":5,"firstName":"Isabella","lastName":"Reed","email":"isabella.reed@example.com","userName":"isareed","passWord":"$2b$10$lnJI4HvVZj9/.hjfIOqeduG0xh6wOaEHMTjjUMgjieU29y3fxbBhK"}]